cuda/bindings/__init__.pxd
cuda/bindings/__init__.py
cuda/bindings/_version.py
cuda/bindings/cufile.cpp
cuda/bindings/cufile.cpython-314t-aarch64-linux-gnu.so
cuda/bindings/cufile.pxd
cuda/bindings/cufile.pyx
cuda/bindings/cycufile.cpp
cuda/bindings/cycufile.cpython-314t-aarch64-linux-gnu.so
cuda/bindings/cycufile.pxd
cuda/bindings/cycufile.pyx
cuda/bindings/cydriver.cpp
cuda/bindings/cydriver.cpython-314t-aarch64-linux-gnu.so
cuda/bindings/cydriver.pxd
cuda/bindings/cydriver.pyx
cuda/bindings/cynvjitlink.cpp
cuda/bindings/cynvjitlink.cpython-314t-aarch64-linux-gnu.so
cuda/bindings/cynvjitlink.pxd
cuda/bindings/cynvjitlink.pyx
cuda/bindings/cynvrtc.cpp
cuda/bindings/cynvrtc.cpython-314t-aarch64-linux-gnu.so
cuda/bindings/cynvrtc.pxd
cuda/bindings/cynvrtc.pyx
cuda/bindings/cynvvm.cpp
cuda/bindings/cynvvm.cpython-314t-aarch64-linux-gnu.so
cuda/bindings/cynvvm.pxd
cuda/bindings/cynvvm.pyx
cuda/bindings/cyruntime.cpp
cuda/bindings/cyruntime.cpython-314t-aarch64-linux-gnu.so
cuda/bindings/cyruntime.pxd
cuda/bindings/cyruntime.pyx
cuda/bindings/cyruntime_functions.pxi
cuda/bindings/cyruntime_types.pxi
cuda/bindings/driver.cpp
cuda/bindings/driver.cpython-314t-aarch64-linux-gnu.so
cuda/bindings/driver.pxd
cuda/bindings/driver.pyx
cuda/bindings/nvjitlink.cpp
cuda/bindings/nvjitlink.cpython-314t-aarch64-linux-gnu.so
cuda/bindings/nvjitlink.pxd
cuda/bindings/nvjitlink.pyx
cuda/bindings/nvrtc.cpp
cuda/bindings/nvrtc.cpython-314t-aarch64-linux-gnu.so
cuda/bindings/nvrtc.pxd
cuda/bindings/nvrtc.pyx
cuda/bindings/nvvm.cpp
cuda/bindings/nvvm.cpython-314t-aarch64-linux-gnu.so
cuda/bindings/nvvm.pxd
cuda/bindings/nvvm.pyx
cuda/bindings/runtime.cpp
cuda/bindings/runtime.cpython-314t-aarch64-linux-gnu.so
cuda/bindings/runtime.pxd
cuda/bindings/runtime.pyx
cuda/bindings/_bindings/__init__.py
cuda/bindings/_bindings/cydriver.cpp
cuda/bindings/_bindings/cydriver.cpython-314t-aarch64-linux-gnu.so
cuda_bindings-13.0.3.dist-info/METADATA
cuda_bindings-13.0.3.dist-info/WHEEL
cuda_bindings-13.0.3.dist-info/top_level.txt
cuda_bindings-13.0.3.dist-info/RECORD
cuda_bindings-13.0.3.dist-info/licenses/LICENSE
