Metadata-Version: 2.4
Name: cuda-bindings
Version: 13.0.3
Summary: Python bindings for CUDA
Author-email: NVIDIA Corporation <cuda-python-conduct@nvidia.com>
License-Expression: LicenseRef-NVIDIA-SOFTWARE-LICENSE
Project-URL: Repository, https://github.com/NVIDIA/cuda-python
Project-URL: Documentation, https://nvidia.github.io/cuda-python/
Classifier: Intended Audience :: Developers
Classifier: Topic :: Database
Classifier: Topic :: Scientific/Engineering
Classifier: Programming Language :: Python
Classifier: Programming Language :: Python :: 3.9
Classifier: Programming Language :: Python :: 3.10
Classifier: Programming Language :: Python :: 3.11
Classifier: Programming Language :: Python :: 3.12
Classifier: Programming Language :: Python :: 3.13
Classifier: Environment :: GPU :: NVIDIA CUDA
License-File: LICENSE
Requires-Dist: cuda-pathfinder~=1.1
Provides-Extra: all
Requires-Dist: cuda-toolkit[nvjitlink,nvrtc,nvvm]==13.*; extra == "all"
Requires-Dist: cuda-toolkit[cufile]==13.*; sys_platform == "linux" and extra == "all"
Dynamic: license-file
